Metadata-Version: 2.1
Name: bwnormalize
Version: 0.0.1
Summary: Converter of dates and monetary values ​for frontend and backend return
Home-page: UNKNOWN
Author: Bruno Ramos
Author-email: brunoramos90@gmail.com
License: MIT
Keywords: dates,currency
Platform: UNKNOWN
Classifier: Development Status :: 5 - Production/Stable
Classifier: Intended Audience :: Education
Classifier: Operating System :: Microsoft :: Windows :: Windows 10
Classifier: License :: OSI Approved :: MIT License
Classifier: Programming Language :: Python :: 3
License-File: LICENSE
